MANIFEST.in
README.txt
setup.py
sffj-astral.ini
xplastral.py
expel.apps.astral.egg-info/PKG-INFO
expel.apps.astral.egg-info/SOURCES.txt
expel.apps.astral.egg-info/dependency_links.txt
expel.apps.astral.egg-info/requires.txt
expel.apps.astral.egg-info/top_level.txt