Metadata-Version: 1.0
Name: expel.apps.astral
Version: 0.1
Summary: xPL Astral - An ExPeL application to output xPL
Home-page: http://www.sffjunkie.co.uk/python-expel.html#astral
Author: Simon Kennedy
Author-email: code@sffjunkie.co.uk
License: Apache-2.0
Platform: UNKNOWN
